LICENSE
MANIFEST.in
README.md
setup.py
galaxybrain/__init__.py
galaxybrain.egg-info/PKG-INFO
galaxybrain.egg-info/SOURCES.txt
galaxybrain.egg-info/dependency_links.txt
galaxybrain.egg-info/requires.txt
galaxybrain.egg-info/top_level.txt
galaxybrain/drivers/__init__.py
galaxybrain/drivers/openai_prompt_driver.py
galaxybrain/drivers/prompt_driver.py
galaxybrain/rules/__init__.py
galaxybrain/rules/json.py
galaxybrain/rules/meta.py
galaxybrain/rules/rule.py
galaxybrain/rules/validator.py
galaxybrain/summarizers/__init__.py
galaxybrain/summarizers/prompt_driver_summarizer.py
galaxybrain/summarizers/summarizer.py
galaxybrain/templates/prompts/conversation.j2
galaxybrain/templates/prompts/input.j2
galaxybrain/templates/prompts/memory.j2
galaxybrain/templates/prompts/rules.j2
galaxybrain/templates/prompts/summarize.j2
galaxybrain/templates/prompts/tool.j2
galaxybrain/templates/prompts/tools.j2
galaxybrain/templates/prompts/steps/prompt.j2
galaxybrain/templates/prompts/steps/tool/substep.j2
galaxybrain/templates/prompts/steps/tool/substeps.j2
galaxybrain/templates/prompts/steps/tool/tool.j2
galaxybrain/tools/__init__.py
galaxybrain/tools/tool.py
galaxybrain/tools/calculator/__init__.py
galaxybrain/tools/calculator/calculator.py
galaxybrain/tools/calculator/examples.j2
galaxybrain/tools/calculator/schema.json
galaxybrain/tools/data_scientist/__init__.py
galaxybrain/tools/data_scientist/data_scientist.py
galaxybrain/tools/data_scientist/examples.j2
galaxybrain/tools/data_scientist/schema.json
galaxybrain/tools/email/__init__.py
galaxybrain/tools/email/email.py
galaxybrain/tools/email/examples.j2
galaxybrain/tools/email/schema.json
galaxybrain/tools/wiki/__init__.py
galaxybrain/tools/wiki/examples.j2
galaxybrain/tools/wiki/schema.json
galaxybrain/tools/wiki/wiki.py
galaxybrain/utils/__init__.py
galaxybrain/utils/j2.py
galaxybrain/utils/python_runner.py
galaxybrain/utils/tiktoken_tokenizer.py
galaxybrain/utils/tokenizer.py
galaxybrain/workflows/__init__.py
galaxybrain/workflows/prompt_step.py
galaxybrain/workflows/step.py
galaxybrain/workflows/step_artifact.py
galaxybrain/workflows/step_input.py
galaxybrain/workflows/step_output.py
