Metadata-Version: 2.1
Name: galaxybrain
Version: 0.1.0
Summary: LLM extensions framework
Home-page: https://github.com/vasinov/galaxybrain
Author: Vasily Vasinov
Author-email: vasinov@me.com
License: Apache 2.0
Platform: UNKNOWN
License-File: LICENSE
